buildenv/__init__.py
buildenv/__main__.py
buildenv/extension.py
buildenv/loader.py
buildenv/manager.py
buildenv/_internal/__init__.py
buildenv/_internal/parser.py
buildenv/_internal/render.py
buildenv/templates/__init__.py
buildenv/templates/activate.cmd.jinja
buildenv/templates/activate.sh.jinja
buildenv/templates/buildenv.cmd.jinja
buildenv/templates/buildenv.sh.jinja
buildenv/templates/command.cmd.jinja
buildenv/templates/command.sh.jinja
buildenv/templates/completion.sh.jinja
buildenv/templates/gitattributes.jinja
buildenv/templates/gitignore.jinja
buildenv/templates/shell.cmd.jinja
buildenv/templates/shell.sh.jinja
buildenv/templates/venv_prompt.sh.jinja
buildenv/templates/warning.jinja
buildenv-1.7.2.dist-info/LICENSE
buildenv-1.7.2.dist-info/METADATA
buildenv-1.7.2.dist-info/WHEEL
buildenv-1.7.2.dist-info/entry_points.txt
buildenv-1.7.2.dist-info/top_level.txt
buildenv-1.7.2.dist-info/RECORD
