Metadata-Version: 2.2
Name: buildenv
Version: 1.7.2
Summary: Build environment setup system, based on Python venv
Author: The dynod project
Maintainer: The dynod project
License: MIT License
Project-URL: Homepage, https://github.com/dynod/buildenv
Project-URL: Repository, https://github.com/dynod/buildenv
Project-URL: Issues, https://github.com/dynod/buildenv/issues?q=is%3Aopen+is%3Aissue
Classifier: Programming Language :: Python :: 3.9
Classifier: Programming Language :: Python :: 3.10
Classifier: Programming Language :: Python :: 3.11
Classifier: Programming Language :: Python :: 3.12
Classifier: Programming Language :: Python :: 3.13
Requires-Python: >=3.9
License-File: LICENSE
Requires-Dist: Jinja2
Requires-Dist: argcomplete
